openwisp_notifications/CONTRIBUTING.rst
openwisp_notifications/__init__.py
openwisp_notifications/admin.py
openwisp_notifications/apps.py
openwisp_notifications/checks.py
openwisp_notifications/context_processors.py
openwisp_notifications/exceptions.py
openwisp_notifications/handlers.py
openwisp_notifications/models.py
openwisp_notifications/settings.py
openwisp_notifications/signals.py
openwisp_notifications/swapper.py
openwisp_notifications/tasks.py
openwisp_notifications/tokens.py
openwisp_notifications/types.py
openwisp_notifications/urls.py
openwisp_notifications/utils.py
openwisp_notifications/views.py
openwisp_notifications/widgets.py
openwisp_notifications/api/__init__.py
openwisp_notifications/api/filters.py
openwisp_notifications/api/permissions.py
openwisp_notifications/api/serializers.py
openwisp_notifications/api/urls.py
openwisp_notifications/api/views.py
openwisp_notifications/base/__init__.py
openwisp_notifications/base/models.py
openwisp_notifications/base/notifications.py
openwisp_notifications/management/__init__.py
openwisp_notifications/management/commands/__init__.py
openwisp_notifications/management/commands/create_notification.py
openwisp_notifications/management/commands/populate_notification_preferences.py
openwisp_notifications/migrations/0001_initial.py
openwisp_notifications/migrations/0002_default_permissions.py
openwisp_notifications/migrations/0003_notification_notification_type.py
openwisp_notifications/migrations/0004_notificationsetting.py
openwisp_notifications/migrations/0005_delete_notificationuser.py
openwisp_notifications/migrations/0006_objectnotification.py
openwisp_notifications/migrations/0007_notificationsetting_deleted.py
openwisp_notifications/migrations/0008_rename_notification_recipient_unread_openwisp_no_recipie_b7c4ef_idx.py
openwisp_notifications/migrations/0009_alter_notificationsetting_organization_and_more.py
openwisp_notifications/migrations/0010_organizationnotificationsettings.py
openwisp_notifications-1.2.dist-info/licenses/LICENSE
openwisp_notifications-1.2.dist-info/METADATA
openwisp_notifications-1.2.dist-info/WHEEL
openwisp_notifications-1.2.dist-info/top_level.txt
openwisp_notifications-1.2.dist-info/RECORD
