Metadata-Version: 2.4
Name: openwisp-notifications
Version: 1.2
Summary: Notifications module of OpenWISP
Home-page: http://openwisp.org
Download-URL: https://github.com/openwisp/openwisp-notifications/releases
Author: OpenWISP
Author-email: support@openwisp.io
License: GPL3
Keywords: django,netjson,notification,openwisp,monitoring
Platform: Platform Independent
Classifier: Development Status :: 5 - Production/Stable
Classifier: Environment :: Web Environment
Classifier: Topic :: Internet :: WWW/HTTP
Classifier: Topic :: System :: Networking
Classifier: Intended Audience :: Developers
Classifier: License :: OSI Approved :: GNU General Public License v3 (GPLv3)
Classifier: Operating System :: OS Independent
Classifier: Framework :: Django
Classifier: Programming Language :: Python :: 3
License-File: LICENSE
Requires-Dist: openwisp-users~=1.2.0
Requires-Dist: openwisp-utils[celery,channels,rest]~=1.2.0
Requires-Dist: markdown~=3.9
Requires-Dist: jsonfield>=2.1.0
Dynamic: author
Dynamic: author-email
Dynamic: classifier
Dynamic: description
Dynamic: download-url
Dynamic: home-page
Dynamic: keywords
Dynamic: license
Dynamic: license-file
Dynamic: platform
Dynamic: requires-dist
Dynamic: summary
